{
  "name": "FindObjects-zio",
  "classSetFunctionFactoryClass": "eu.cdevreeze.tryreflection.introspection.classsetfunctions.FindClasses$",
  "classSetFunctionFactoryJsonInput": {
    "ignoreInterface": true,
    "ignoreAbstractClass": true,
    "classSections": [
      {
        "description": "ZIO Effect",
        "showConstructors": false,
        "classFilters": [
          {
            "kindOfFilter": "AssignableTo",
            "filterValue": "zio.ZIO"
          }
        ]
      },
      {
        "description": "ZIO Layer",
        "showConstructors": false,
        "classFilters": [
          {
            "kindOfFilter": "AssignableTo",
            "filterValue": "zio.ZLayer"
          }
        ]
      }
    ]
  }
}